posce/__init__.py
posce/__main__.py
posce/comms/__init__.py
posce/comms/base.py
posce/comms/clip.py
posce/comms/copy.py
posce/comms/drop.py
posce/comms/dump.py
posce/comms/edit.py
posce/comms/find.py
posce/comms/list.py
posce/comms/make.py
posce/comms/move.py
posce/comms/repl.py
posce/comms/show.py
posce/comms/wget.py
posce/items/__init__.py
posce/items/book.py
posce/items/note.py
posce/tools/__init__.py
posce/tools/clui.py
posce/tools/file.py
posce/tools/path.py
posce-1.0.0.dist-info/METADATA
posce-1.0.0.dist-info/WHEEL
posce-1.0.0.dist-info/entry_points.txt
posce-1.0.0.dist-info/license.md
posce-1.0.0.dist-info/top_level.txt
posce-1.0.0.dist-info/RECORD
