Metadata-Version: 2.1
Name: posce
Version: 1.0.0
Summary: A note-taking toolkit for your command line.
Home-page: https://github.com/posce/posce
Author: Stephen Malone
Author-email: mail@posce.org
License: UNKNOWN
Project-URL: Homepage, https://github.com/posce/posce
Project-URL: Issues, https://github.com/posce/posce/issues
Keywords: cli notes note-taking
Platform: UNKNOWN
Classifier: Development Status :: 3 - Alpha
Classifier: Environment :: Console
Classifier: Intended Audience :: End Users/Desktop
Classifier: License :: OSI Approved :: BSD License
Classifier: Natural Language :: English
Classifier: Programming Language :: Python :: 3 :: Only
Classifier: Programming Language :: Python :: 3.8
Classifier: Topic :: Office/Business :: News/Diary
Classifier: Topic :: Office/Business
Requires-Python: >=3.8.0
Requires-Dist: click (>=7.1.1)
Requires-Dist: pyperclip (>=1.7.0)
Requires-Dist: Send2Trash (>=1.5.0)
